{"frames": {

"joe_1.png":
{
	"frame": {"x":0,"y":0,"w":64,"h":64},
	"rotated": false,
	"trimmed": false,
	"spriteSourceSize": {"x":0,"y":0,"w":64,"h":64},
	"sourceSize": {"w":64,"h":64}
},
"joe_2.png":
{
	"frame": {"x":0,"y":64,"w":64,"h":64},
	"rotated": false,
	"trimmed": false,
	"spriteSourceSize": {"x":0,"y":0,"w":64,"h":64},
	"sourceSize": {"w":64,"h":64}
},
"joe_3.png":
{
	"frame": {"x":0,"y":128,"w":64,"h":64},
	"rotated": false,
	"trimmed": false,
	"spriteSourceSize": {"x":0,"y":0,"w":64,"h":64},
	"sourceSize": {"w":64,"h":64}
},
"joe_4.png":
{
	"frame": {"x":0,"y":192,"w":64,"h":64},
	"rotated": false,
	"trimmed": false,
	"spriteSourceSize": {"x":0,"y":0,"w":64,"h":64},
	"sourceSize": {"w":64,"h":64}
},
"joe_5.png":
{
	"frame": {"x":0,"y":256,"w":64,"h":64},
	"rotated": false,
	"trimmed": false,
	"spriteSourceSize": {"x":0,"y":0,"w":64,"h":64},
	"sourceSize": {"w":64,"h":64}
}},
"meta": {
	"app": "https://www.codeandweb.com/texturepacker",
	"version": "1.0",
	"image": "joe.png",
	"format": "RGBA8888",
	"size": {"w":64,"h":320},
	"scale": "1",
	"smartupdate": "$TexturePacker:SmartUpdate:326a69fe8c2082973655cadf42092687:fba0c5c99a1e8415ecde957be22a9fb1:ec48e414b7288dd96be9f781c75c7a4c$"
}
}
